phone_number_validator_gr81/__init__.py
phone_number_validator_gr81/validator.py
phone_number_validator_gr81-0.1.0.dist-info/METADATA
phone_number_validator_gr81-0.1.0.dist-info/WHEEL
phone_number_validator_gr81-0.1.0.dist-info/RECORD
