Metadata-Version: 2.1
Name: phone-number-validator-gr81
Version: 0.1.0
Summary: 
Author: peter.landy
Author-email: peter.landy@icloud.com
Requires-Python: >=3.11,<4.0
Classifier: Programming Language :: Python :: 3
Classifier: Programming Language :: Python :: 3.11
Requires-Dist: requests (>=2.31.0,<3.0.0)
